nhmail/__init__.py
nhmail/client.py
nhmail/constants.py
nhmail/validators.py
nhmail-2.0.1.dist-info/LICENSE
nhmail-2.0.1.dist-info/METADATA
nhmail-2.0.1.dist-info/WHEEL
nhmail-2.0.1.dist-info/top_level.txt
nhmail-2.0.1.dist-info/RECORD
