Metadata-Version: 2.1
Name: nhmail
Version: 2.0.1
Summary: email of nandh SDK for Python
Home-page: https://github.com/ITNHL/nh-mail-sdk
Author: it@nandhlogistics.vn
Author-email: it@nandhlogistics.vn
License: Version 1.0
Classifier: Intended Audience :: Developers
Classifier: Programming Language :: Python
Provides: nhmail
License-File: LICENSE
Requires-Dist: pre-commit ==3.6.2
Requires-Dist: marshmallow ==3.19.0
Requires-Dist: requests ==2.31.0
